<odoo>
    <data>

        <record model="ir.actions.act_window" id="action_hr_executing_provisions">
            <field name="name">Ejecutar Provisiones</field>
            <field name="res_model">hr.executing.provisions</field>
            <field name="view_mode">tree,form</field>
        </record>

        <!-- Crear record rule para filtrar las compa침ias-->
        <record id="rule_hr_payroll_provisions_company" model="ir.rule">
            <field name="name">Permisos compa침ia Provisiones</field>
            <field name="model_id" ref="model_hr_executing_provisions"/>
            <field name="domain_force">['|',('company_id','=',False),('company_id', 'in', company_ids)]</field>
        </record>

        <record model="ir.ui.view" id="hr_executing_provisions_list">
            <field name="name">hr executing provisions list</field>
            <field name="model">hr.executing.provisions</field>
            <field name="arch" type="xml">
                <tree>
                    <field name="year"/>
                    <field name="month"/>
                    <field name="company_id"/>
                    <field name="observations"/>
                </tree>
            </field>
        </record>

        <record model="ir.ui.view" id="hr_executing_provisions_form">
            <field name="name">hr executing provisions form</field>
            <field name="model">hr.executing.provisions</field>
            <field name="arch" type="xml">
                <form>
                    <header>
                        <button name="executing_provisions" type="object" string="Provisionar" class="oe_highlight" invisible="state != 'draft'"/>
                        <button name="get_accounting" type="object" string="Contabilizar" class="oe_highlight" invisible="state != 'done'"/>
                        <button name="cancel_process" type="object" string="Cancelar" invisible="state not in ['draft', 'done']"/>
                        <button name="restart_accounting" type="object" string="Reiniciar Contabilizaci칩n" invisible="state != 'accounting'"/>
                        <field name="state" widget="statusbar"/>
                    </header>
                    <sheet>
                        <group>
                            <group string="Periodo">
                                <field name="year"/>
                                <field name="month"/>
                            </group>
                            <group string="Observaciones">
                                <field name="observations" nolabel="1"/>
                            </group>
                        </group>
                        <group>
                            <field name="company_id"/>
                            <field name="time_process" readonly="1"/>
                        </group>
                        <notebook>
                            <page string="Ejecuci칩n">
                                <field name="details_ids" readonly="1" force_save="1">
                                    <tree>
                                        <field name="provision"/>
                                        <field name="employee_id"/>
                                        <field name="contract_id" optional="show"/>
                                        <field name="value_wage" optional="show"/>
                                        <field name="value_base" optional="show"/>
                                        <field name="time" optional="show"/>
                                        <field name="amount" optional="show"/>
                                        <field name="value_payments" optional="show"/>
                                        <field name="current_payable_value" optional="show"/>
                                        <field name="value_balance" optional="show"/>
                                    </tree>
                                </field>
                            </page>
                        </notebook>
                        <group>
                            <field name="move_id" readonly="1"/>
                        </group>
                    </sheet>
                </form>
            </field>
        </record>
    </data>
</odoo>